codestory/__init__.py
codestory/__main__.py
codestory/cli.py
codestory/constants.py
codestory/context.py
codestory/onboarding.py
codestory/runtimeutil.py
codestory/commands/__init__.py
codestory/commands/clean.py
codestory/commands/commit.py
codestory/commands/config.py
codestory/commands/fix.py
codestory/core/__init__.py
codestory/core/exceptions.py
codestory/core/validation.py
codestory/core/config/config_loader.py
codestory/core/config/type_constraints.py
codestory/core/diff/creation/atomic_chunker.py
codestory/core/diff/creation/diff_creator.py
codestory/core/diff/creation/hunk_wrapper.py
codestory/core/diff/creation/immutable_hunk_wrapper.py
codestory/core/diff/data/atomic_chunk.py
codestory/core/diff/data/atomic_container.py
codestory/core/diff/data/commit_group.py
codestory/core/diff/data/composite_container.py
codestory/core/diff/data/immutable_diff_chunk.py
codestory/core/diff/data/line_changes.py
codestory/core/diff/data/single_container.py
codestory/core/diff/data/standard_diff_chunk.py
codestory/core/diff/data/utils.py
codestory/core/diff/patch/git_patch_generator.py
codestory/core/diff/patch/patch_generator.py
codestory/core/diff/patch/semantic_patch_generator.py
codestory/core/diff/pipeline/filter.py
codestory/core/diff/pipeline/grouper.py
codestory/core/diff/utils/chunk_merger.py
codestory/core/embeddings/clusterer.py
codestory/core/embeddings/embedder.py
codestory/core/file_parser/file_parser.py
codestory/core/file_parser/language_mapper.py
codestory/core/filters/cmd_user_filter.py
codestory/core/filters/relevance_filter.py
codestory/core/filters/secret_filter.py
codestory/core/filters/utils.py
codestory/core/git/git_commands.py
codestory/core/git/git_const.py
codestory/core/git/git_interface.py
codestory/core/git/git_rebaser.py
codestory/core/git/git_sandbox.py
codestory/core/git/git_synthesizer.py
codestory/core/git/git_temp_commiter.py
codestory/core/groupers/embedding_grouper.py
codestory/core/groupers/single_grouper.py
codestory_cli-0.1.12.dist-info/METADATA
codestory_cli-0.1.12.dist-info/WHEEL
codestory_cli-0.1.12.dist-info/entry_points.txt
codestory_cli-0.1.12.dist-info/top_level.txt
codestory_cli-0.1.12.dist-info/RECORD
