Metadata-Version: 2.4
Name: codestory-cli
Version: 0.1.12
Summary: Every project should have a good story behind it. With a good story (git history), you can reason about changes in a way that would be impossible just looking at a codebase. But let us do the work in creating that story
Author-email: Adem Can <ademfcan@gmail.com>
License-Expression: GPL-2.0-only
Requires-Python: >=3.11
Requires-Dist: typer-slim==0.20.0
Requires-Dist: colorama==0.4.6
Requires-Dist: loguru==0.7.3
Requires-Dist: tree-sitter==0.25.2
Requires-Dist: tree-sitter-language-pack==0.13.0
Requires-Dist: platformdirs==4.5.0
Requires-Dist: tqdm==4.67.1
Requires-Dist: fastembed>=0.7.4
Requires-Dist: scikit-learn<1.9.0,>=1.8.0
Requires-Dist: networkx<4.0,>=3.0
Requires-Dist: python-dotenv>=1.2.1
Requires-Dist: aisuite-extendedmodels[anthropic,aws,azure,cerebras,cohere,deepseek,googlegenai,groq,huggingface,mcp,mistral,ollama,openai,watsonx]>=0.1.15
Provides-Extra: dev
Requires-Dist: pytest; extra == "dev"
Requires-Dist: pytest-cov; extra == "dev"
Requires-Dist: ruff; extra == "dev"
Requires-Dist: mypy; extra == "dev"
Requires-Dist: mkdocs; extra == "dev"
Requires-Dist: mkdocs-material; extra == "dev"
Requires-Dist: mkdocs-typer2; extra == "dev"
